README.rst
setup.py
ajaxtoolkit/__init__.py
ajaxtoolkit/http.py
ajaxtoolkit/jsonwrapper.py
ajaxtoolkit/middleware.py
ajaxtoolkit/models.py
ajaxtoolkit/tests.py
django_ajax_toolkit.egg-info/PKG-INFO
django_ajax_toolkit.egg-info/SOURCES.txt
django_ajax_toolkit.egg-info/dependency_links.txt
django_ajax_toolkit.egg-info/requires.txt
django_ajax_toolkit.egg-info/top_level.txt