Metadata-Version: 1.0
Name: django-ajax-toolkit
Version: 0.2.2
Summary: Ajax goodies for django projects.
Home-page: https://github.com/Geekfish/django-ajax-toolkit
Author: Eleni Lixourioti
Author-email: contact@eleni.co
License: BSD
Keywords: django,ajax,utilities,http
Platform: linux
Classifier: Environment :: Web Environment
Classifier: Framework :: Django
Classifier: Intended Audience :: Developers
Classifier: License :: OSI Approved :: BSD License
Classifier: Operating System :: Unix
Classifier: Development Status :: 3 - Alpha
Classifier: Programming Language :: Python
